index.py
spellingbee_mcp-0.1.0.dist-info/METADATA
spellingbee_mcp-0.1.0.dist-info/WHEEL
spellingbee_mcp-0.1.0.dist-info/entry_points.txt
spellingbee_mcp-0.1.0.dist-info/top_level.txt
spellingbee_mcp-0.1.0.dist-info/RECORD
